grafana_client/__init__.py
grafana_client/api.py
grafana_client/client.py
grafana_client/knowledge.py
grafana_client/model.py
grafana_client/util.py
grafana_client/version.py
grafana_client/elements/__init__.py
grafana_client/elements/admin.py
grafana_client/elements/alerting.py
grafana_client/elements/alertingprovisioning.py
grafana_client/elements/annotations.py
grafana_client/elements/base.py
grafana_client/elements/dashboard.py
grafana_client/elements/dashboard_versions.py
grafana_client/elements/datasource.py
grafana_client/elements/folder.py
grafana_client/elements/health.py
grafana_client/elements/libraryelement.py
grafana_client/elements/notifications.py
grafana_client/elements/organization.py
grafana_client/elements/plugin.py
grafana_client/elements/rbac.py
grafana_client/elements/search.py
grafana_client/elements/service_account.py
grafana_client/elements/snapshots.py
grafana_client/elements/team.py
grafana_client/elements/user.py
grafana_client/elements/_async/__init__.py
grafana_client/elements/_async/admin.py
grafana_client/elements/_async/alerting.py
grafana_client/elements/_async/alertingprovisioning.py
grafana_client/elements/_async/annotations.py
grafana_client/elements/_async/dashboard.py
grafana_client/elements/_async/dashboard_versions.py
grafana_client/elements/_async/datasource.py
grafana_client/elements/_async/folder.py
grafana_client/elements/_async/health.py
grafana_client/elements/_async/libraryelement.py
grafana_client/elements/_async/notifications.py
grafana_client/elements/_async/organization.py
grafana_client/elements/_async/plugin.py
grafana_client/elements/_async/rbac.py
grafana_client/elements/_async/search.py
grafana_client/elements/_async/service_account.py
grafana_client/elements/_async/snapshots.py
grafana_client/elements/_async/team.py
grafana_client/elements/_async/user.py
grafana_client-5.0.1.dist-info/licenses/LICENSE
test/elements/__init__.py
test/elements/test_admin.py
test/elements/test_alerting.py
test/elements/test_alertingprovisioning.py
grafana_client-5.0.1.dist-info/METADATA
grafana_client-5.0.1.dist-info/WHEEL
grafana_client-5.0.1.dist-info/top_level.txt
grafana_client-5.0.1.dist-info/RECORD
