Metadata-Version: 2.4
Name: grafana-client
Version: 5.0.1
Summary: A client library for accessing the Grafana HTTP API, written in Python
Home-page: https://github.com/grafana-toolbox/grafana-client
Author: Andrew Prokhorenkov
Author-email: andrew.prokhorenkov@gmail.com
Maintainer: Andreas Motl
Maintainer-email: andreas.motl@panodata.org
License: MIT
Project-URL: Source, https://github.com/grafana-toolbox/grafana-client
Project-URL: Tracker, https://github.com/grafana-toolbox/grafana-client/issues
Keywords: grafana http api grafana-client grafana-api http-client grafana-utils grafana-automation grafana-toolbox
Classifier: Development Status :: 5 - Production/Stable
Classifier: Environment :: Console
Classifier: Environment :: Web Environment
Classifier: Intended Audience :: Developers
Classifier: Intended Audience :: Education
Classifier: Intended Audience :: Information Technology
Classifier: Intended Audience :: Manufacturing
Classifier: Intended Audience :: Science/Research
Classifier: Intended Audience :: System Administrators
Classifier: Intended Audience :: Telecommunications Industry
Classifier: License :: OSI Approved :: MIT License
Classifier: Operating System :: OS Independent
Classifier: Programming Language :: Python
Classifier: Programming Language :: Python :: 3
Classifier: Programming Language :: Python :: 3.7
Classifier: Programming Language :: Python :: 3.8
Classifier: Programming Language :: Python :: 3.9
Classifier: Programming Language :: Python :: 3.10
Classifier: Programming Language :: Python :: 3.11
Classifier: Programming Language :: Python :: 3.12
Classifier: Programming Language :: Python :: 3.13
Classifier: Programming Language :: Python :: Implementation :: CPython
Classifier: Programming Language :: Python :: Implementation :: PyPy
Classifier: Topic :: Communications
Classifier: Topic :: Database
Classifier: Topic :: Internet
Classifier: Topic :: Internet :: WWW/HTTP
Classifier: Topic :: Scientific/Engineering
Classifier: Topic :: Scientific/Engineering :: Human Machine Interfaces
Classifier: Topic :: Scientific/Engineering :: Information Analysis
Classifier: Topic :: Scientific/Engineering :: Interface Engine/Protocol Translator
Classifier: Topic :: Scientific/Engineering :: Visualization
Classifier: Topic :: Software Development
Classifier: Topic :: Software Development :: Libraries
Classifier: Topic :: Software Development :: Libraries :: Python Modules
Classifier: Topic :: System :: Archiving
Classifier: Topic :: System :: Networking :: Monitoring
Classifier: Topic :: Utilities
Classifier: Operating System :: MacOS
Classifier: Operating System :: OS Independent
Classifier: Operating System :: POSIX
Classifier: Operating System :: Unix
Requires-Python: >=3.7
License-File: LICENSE
Requires-Dist: niquests<4,>=3.4.0
Requires-Dist: importlib-metadata; python_version <= "3.7"
Requires-Dist: verlib2<0.4
Provides-Extra: test
Requires-Dist: parameterized<1,>=0.8; extra == "test"
Requires-Dist: codecov<3; extra == "test"
Requires-Dist: coverage[toml]<8; extra == "test"
Requires-Dist: unittest-xml-reporting<4; extra == "test"
Requires-Dist: requests-mock<2; extra == "test"
Provides-Extra: develop
Requires-Dist: build<2; extra == "develop"
Requires-Dist: poethepoet<1; extra == "develop"
Requires-Dist: pip-review<2; extra == "develop"
Requires-Dist: ruff<0.13; python_version >= "3.7" and extra == "develop"
Requires-Dist: twine<7; extra == "develop"
Dynamic: license-file
